core.py
minilang-1.2.0.dist-info/METADATA
minilang-1.2.0.dist-info/WHEEL
minilang-1.2.0.dist-info/top_level.txt
minilang-1.2.0.dist-info/RECORD
