Metadata-Version: 2.4
Name: minilang
Version: 1.2.0
Summary: A simple way to create a mini programing language
Author-email: Bob Robertson <Coderdude123@proton.me>
License: MIT
Project-URL: Homepage, https://github.com/Jeff-web-sketch/minilang_lib_for_python/tree/main/minilang
Requires-Python: >=3.7
